Metadata-Version: 2.4
Name: flask-inertia
Version: 0.10
Summary: Inertiajs Adapter for Flask.
Home-page: https://github.com/j0ack/flask-inertia
Author: TROUVERIE Joachim
Author-email: jtrouverie@joakode.fr
License: MIT
Platform: any
Classifier: Development Status :: 5 - Production/Stable
Classifier: License :: OSI Approved :: MIT License
Classifier: Environment :: Web Environment
Classifier: Intended Audience :: Developers
Classifier: Operating System :: OS Independent
Classifier: Framework :: Flask
Classifier: Programming Language :: Python :: 3
Classifier: Topic :: Internet :: WWW/HTTP :: Dynamic Content
Classifier: Topic :: Software Development :: Libraries :: Python Modules
Classifier: Topic :: Utilities
License-File: LICENSE
Requires-Dist: Flask>=1.1.2
Requires-Dist: jsmin>=2.2.2
Provides-Extra: tests
Requires-Dist: beautifulsoup4>=4.10.0; extra == "tests"
Dynamic: author
Dynamic: author-email
Dynamic: classifier
Dynamic: description
Dynamic: home-page
Dynamic: license
Dynamic: license-file
Dynamic: platform
Dynamic: provides-extra
Dynamic: requires-dist
Dynamic: summary
